Metadata-Version: 2.1
Name: py-strict-typing
Version: 0.1.0
Summary: A library for enforcing strict typing of class members and function parameters in Python.
Home-page: https://github.com/whdev1/py-strict-typing
Author: whdev1
Author-email: whdev1@protonmail.com
License: MIT
Download-URL: https://github.com/whdev1/py-strict-typing/archive/refs/tags/v0.1.0.tar.gz
Keywords: Strict,Typing,Type-checking,Decorator,py-strict-typing
Platform: UNKNOWN
Classifier: Development Status :: 3 - Alpha
Classifier: Intended Audience :: Developers
Classifier: Topic :: Software Development :: Build Tools
Classifier: License :: OSI Approved :: MIT License
Classifier: Programming Language :: Python :: 3.7
Classifier: Programming Language :: Python :: 3.8
Classifier: Programming Language :: Python :: 3.9
License-File: LICENSE.txt
